hubblax/__init__.py
hubblax/covariance.py
hubblax/fitter.py
hubblax/hubblax.py
hubblax/likelihood.py
hubblax-0.3.1.dist-info/LICENSE
hubblax-0.3.1.dist-info/METADATA
hubblax-0.3.1.dist-info/WHEEL
hubblax-0.3.1.dist-info/top_level.txt
hubblax-0.3.1.dist-info/RECORD
